Metadata-Version: 2.1
Name: FormulaBasedMaterials
Version: 0.2.2
Summary: A code for generating Formula-Based Materials into Voxel, STL files.
Home-page: https://github.com/MicDonald/FormulaBasedMaterials
Author: Michael, Yu-Chuan, Hsu
Author-email: mk60503mk60503@gmail.com
License: MIT
Keywords: Formula-Based,3D printing,stl,voxel,surface
Platform: UNKNOWN
Classifier: Programming Language :: Python :: 3
Classifier: License :: OSI Approved :: MIT License
Classifier: Operating System :: OS Independent
Requires-Python: >=3.6
